apksigtool.py
apksigtool-0.1.0.dist-info/LICENSE.AGPLv3
apksigtool-0.1.0.dist-info/METADATA
apksigtool-0.1.0.dist-info/WHEEL
apksigtool-0.1.0.dist-info/entry_points.txt
apksigtool-0.1.0.dist-info/top_level.txt
apksigtool-0.1.0.dist-info/RECORD
